passpie/__init__.py
passpie/_compat.py
passpie/checkers.py
passpie/cli.py
passpie/clipboard.py
passpie/completion.py
passpie/config.py
passpie/credential.py
passpie/crypt.py
passpie/database.py
passpie/history.py
passpie/process.py
passpie/table.py
passpie/utils.py
passpie/validators.py
passpie/importers/__init__.py
passpie/importers/csv_importer.py
passpie/importers/default_importer.py
passpie/importers/keepass_importer.py
passpie/importers/pysswords_importer.py
passpie-1.6.1.dist-info/DESCRIPTION.rst
passpie-1.6.1.dist-info/METADATA
passpie-1.6.1.dist-info/RECORD
passpie-1.6.1.dist-info/WHEEL
passpie-1.6.1.dist-info/entry_points.txt
passpie-1.6.1.dist-info/metadata.json
passpie-1.6.1.dist-info/top_level.txt
tests/__init__.py
tests/conftest.py
tests/helpers.py
tests/test_checkers.py
tests/test_cli.py
tests/test_clipboard.py
tests/test_completion.py
tests/test_config.py
tests/test_credential.py
tests/test_crypt.py
tests/test_database.py
tests/test_history.py
tests/test_process.py
tests/test_table.py
tests/test_utils.py
tests/test_validators.py
tests/test_importers/__init__.py
tests/test_importers/test_base_importer.py
tests/test_importers/test_csv_importer.py
tests/test_importers/test_default_importer.py
tests/test_importers/test_keepass_importer.py
tests/test_importers/test_pysswords_importer.py
