Metadata-Version: 2.0
Name: passpie
Version: 1.6.1
Summary: Manage your login credentials from the terminal painlessly.
Home-page: https://github.com/marcwebbie/passpie
Author: Marcwebbie
Author-email: marcwebbie@gmail.com
License: License :: OSI Approved :: MIT License
Download-URL: https://github.com/marcwebbie/passpie
Platform: UNKNOWN
Classifier: Development Status :: 4 - Beta
Classifier: Environment :: Console
Classifier: Intended Audience :: End Users/Desktop
Classifier: License :: OSI Approved :: MIT License
Classifier: Natural Language :: English
Classifier: Operating System :: OS Independent
Classifier: Programming Language :: Python :: 2.7
Classifier: Programming Language :: Python :: 3
Classifier: Programming Language :: Python :: 3.3
Classifier: Programming Language :: Python :: 3.4
Classifier: Programming Language :: Python :: Implementation :: CPython
Classifier: Programming Language :: Python :: Implementation :: PyPy
Classifier: Programming Language :: Python
Classifier: Topic :: Security :: Cryptography
Requires-Dist: click (==6.6)
Requires-Dist: PyYAML (==3.11)
Requires-Dist: tabulate (==0.7.5)
Requires-Dist: tinydb (==3.2.1)
Requires-Dist: rstr (==2.2.4)
